fabricatio_plot/__init__.py
fabricatio_plot/config.py
fabricatio_plot/py.typed
fabricatio_plot/actions/__init__.py
fabricatio_plot/actions/fs.py
fabricatio_plot/actions/plot.py
fabricatio_plot/actions/synthesize.py
fabricatio_plot/capabilities/__init__.py
fabricatio_plot/capabilities/plot.py
fabricatio_plot/capabilities/synthesize_data.py
fabricatio_plot/models/__init__.py
fabricatio_plot/toolboxes/__init__.py
fabricatio_plot/toolboxes/dataframe_curd.py
fabricatio_plot/toolboxes/dataframe_io.py
fabricatio_plot/toolboxes/plot.py
fabricatio_plot/toolboxes/synthesize.py
fabricatio_plot/workflows/__init__.py
tests/test_data_curd_tools.py
tests/test_data_io_tools.py
tests/test_fabricatio_plot.py
tests/test_plot_tools.py
tests/test_synthesize_data.py
fabricatio_plot-0.1.11.dist-info/METADATA
fabricatio_plot-0.1.11.dist-info/WHEEL
fabricatio_plot-0.1.11.dist-info/licenses/LICENSE
fabricatio_plot-0.1.11.dist-info/RECORD
