Metadata-Version: 2.4
Name: fabricatio-plot
Version: 0.1.11
Summary: An extension of fabricatio, which brings up the capability to plot dataframe with matplotlib
Project-URL: Homepage, https://github.com/Whth/fabricatio
Project-URL: Repository, https://github.com/Whth/fabricatio
Project-URL: Issues, https://github.com/Whth/fabricatio/issues
Author-email: Whth <zettainspector@foxmail.com>
License: MIT License
License-File: LICENSE
Classifier: License :: OSI Approved :: MIT License
Classifier: Programming Language :: Python :: 3.12
Classifier: Programming Language :: Python :: 3.13
Classifier: Programming Language :: Python :: 3.14
Classifier: Programming Language :: Python :: Implementation :: CPython
Classifier: Typing :: Typed
Requires-Python: <3.15,>=3.12
Requires-Dist: fabricatio-core
Requires-Dist: fabricatio-tool
Requires-Dist: matplotlib>=3.10.3
Requires-Dist: numpy>=2.3.0
Requires-Dist: pandas>=2.3.0
Provides-Extra: excel
Requires-Dist: openpyxl>=3.1.5; extra == 'excel'
Provides-Extra: parquet
Requires-Dist: pyarrow>=15.0.0; extra == 'parquet'
